iiitb_pwm_gen.v
module iiitb_pwm_gen
 (
 clk, // 100MHz clock input 
 increase_duty, // input to increase 10% duty cycle 
 decrease_duty, // input to decrease 10% duty cycle 
 PWM_OUT // 10MHz PWM output signal 
    );
 
 input clk;
 input increase_duty;
 input decrease_duty;
 output PWM_OUT;
 wire slow_clk_enable; // slow clock enable signal for debouncing FFs
 reg[27:0] counter_debounce=0;// counter for creating slow clock enable signals 
 wire tmp1,tmp2,duty_inc;// temporary flip-flop signals for debouncing the increasing button
 wire tmp3,tmp4,duty_dec;// temporary flip-flop signals for debouncing the decreasing button
 reg[3:0] counter_PWM=0;// counter for creating 10Mhz PWM signal
 reg[3:0] DUTY_CYCLE=5; // initial duty cycle is 50%
  // Debouncing 2 buttons for inc/dec duty cycle 
  // Firstly generate slow clock enable for debouncing flip-flop (4Hz)
 always @(posedge clk)
 begin
   counter_debounce <= counter_debounce + 1;
   //if(counter_debounce>=25000000) then  
   // for running on FPGA -- comment when running simulation
   if(counter_debounce>=1) 
   // for running simulation -- comment when running on FPGA
    counter_debounce <= 0;
 end
 // assign slow_clk_enable = counter_debounce == 25000000 ?1:0;
 // for running on FPGA -- comment when running simulation 
 assign slow_clk_enable = counter_debounce == 1 ?1:0;
 // for running simulation -- comment when running on FPGA
 // debouncing FFs for increasing button
 DFF_PWM PWM_DFF1(clk,slow_clk_enable,increase_duty,tmp1);
 DFF_PWM PWM_DFF2(clk,slow_clk_enable,tmp1, tmp2); 
 assign duty_inc =  tmp1 & (~ tmp2) & slow_clk_enable;
 // debouncing FFs for decreasing button
 DFF_PWM PWM_DFF3(clk,slow_clk_enable,decrease_duty, tmp3);
 DFF_PWM PWM_DFF4(clk,slow_clk_enable,tmp3, tmp4); 
 assign duty_dec =  tmp3 & (~ tmp4) & slow_clk_enable;
 // vary the duty cycle using the debounced buttons above
 always @(posedge clk)
 begin
   if(duty_inc==1 && DUTY_CYCLE <= 9) 
    DUTY_CYCLE <= DUTY_CYCLE + 1;// increase duty cycle by 10%
   else if(duty_dec==1 && DUTY_CYCLE>=1) 
    DUTY_CYCLE <= DUTY_CYCLE - 1;//decrease duty cycle by 10%
 end 
// Create 10MHz PWM signal with variable duty cycle controlled by 2 buttons 
 always @(posedge clk)
 begin
   counter_PWM <= counter_PWM + 1;
   if(counter_PWM>=9) 
    counter_PWM <= 0;
 end
 assign PWM_OUT = counter_PWM < DUTY_CYCLE ? 1:0;
endmodule
// Debouncing DFFs for push buttons on FPGA
module DFF_PWM(clk,en,D,Q);
input clk,en,D;
output reg Q;
always @(posedge clk)
begin 
 if(en==1) // slow clock enable signal 
  Q <= D;
end 
endmodule

iiitb_pwm_gen_tb.v
`timescale 1ns / 1ps
`include "iiitb_pwm_gen.v"
module iiitb_pwm_gen_tb;  
 // Inputs
 reg clk;
 reg increase_duty;
 reg decrease_duty;
 // Outputs
 wire PWM_OUT;
 // Instantiate the PWM Generator with variable duty cycle in Verilog
 iiitb_pwm_gen PWM_Generator_Unit(
  .clk(clk), 
  .increase_duty(increase_duty), 
  .decrease_duty(decrease_duty), 
  .PWM_OUT(PWM_OUT)
 );
 // Create 100Mhz clock
 initial 
    begin
	//for creating vcd waveform file to view in gtkwave
	
	$dumpfile ("pwm.vcd"); //by default vcd
	$dumpvars(0, iiitb_pwm_gen_tb);
    end
 initial begin
 clk = 0;
 forever #5 clk = ~clk;
 end 
 initial begin
  increase_duty = 0;
  decrease_duty = 0;
  #100; 
    increase_duty = 1; 
  #100;// increase duty cycle by 10%
    increase_duty = 0;
  #100; 
    increase_duty = 1;
  #100;// increase duty cycle by 10%
    increase_duty = 0;
  #100; 
    increase_duty = 1;
  #100;// increase duty cycle by 10%
    increase_duty = 0;
  #100; 
    increase_duty = 1; 
  #100;// increase duty cycle by 10%
    increase_duty = 0;
  #100; 
    increase_duty = 1;
  #100;// increase duty cycle by 10%
    increase_duty = 0;
  #100;
    decrease_duty = 1; 
  #100;//decrease duty cycle by 10%
    decrease_duty = 0;
  #100; 
    decrease_duty = 1;
  #100;//decrease duty cycle by 10%
    decrease_duty = 0;
  #100;
    decrease_duty = 1;
  #100;//decrease duty cycle by 10%
    decrease_duty = 0;
  #100;
    decrease_duty = 1; 
  #100;//decrease duty cycle by 10%
    decrease_duty = 0;
  #100; 
    decrease_duty = 1;
  #100;//decrease duty cycle by 10%
    decrease_duty = 0;
  #100;
    decrease_duty = 1;
  #100;//decrease duty cycle by 10%
    decrease_duty = 0;
    #100;
    decrease_duty = 1; 
  #100;//decrease duty cycle by 10%
    decrease_duty = 0;
  #100; 
    decrease_duty = 1;
  #100;//decrease duty cycle by 10%
    decrease_duty = 0;
  #100;
    decrease_duty = 1;
  #100;//decrease duty cycle by 10%
    decrease_duty = 0;
  #100 $finish;
 end
endmodule

pwm_funct.vcd
$date
	Sun Aug  7 11:36:13 2022
$end
$version
	Icarus Verilog
$end
$timescale
	1ps
$end
$scope module iiitb_pwm_gen_tb $end
$var wire 1 ! PWM_OUT $end
$var reg 1 " clk $end
$var reg 1 # decrease_duty $end
$var reg 1 $ increase_duty $end
$scope module PWM_Generator_Unit $end
$var wire 1 " clk $end
$var wire 1 # decrease_duty $end
$var wire 1 % duty_dec $end
$var wire 1 & duty_inc $end
$var wire 1 $ increase_duty $end
$var wire 1 ' tmp4 $end
$var wire 1 ( tmp3 $end
$var wire 1 ) tmp2 $end
$var wire 1 * tmp1 $end
$var wire 1 + slow_clk_enable $end
$var wire 1 ! PWM_OUT $end
$var reg 4 , DUTY_CYCLE [3:0] $end
$var reg 4 - counter_PWM [3:0] $end
$var reg 28 . counter_debounce [27:0] $end
$scope module PWM_DFF1 $end
$var wire 1 $ D $end
$var wire 1 " clk $end
$var wire 1 + en $end
$var reg 1 * Q $end
$upscope $end
$scope module PWM_DFF2 $end
$var wire 1 * D $end
$var wire 1 " clk $end
$var wire 1 + en $end
$var reg 1 ) Q $end
$upscope $end
$scope module PWM_DFF3 $end
$var wire 1 # D $end
$var wire 1 " clk $end
$var wire 1 + en $end
$var reg 1 ( Q $end
$upscope $end
$scope module PWM_DFF4 $end
$var wire 1 ( D $end
$var wire 1 " clk $end
$var wire 1 + en $end
$var reg 1 ' Q $end
$upscope $end
$upscope $end
$upscope $end
$enddefinitions $end
#0
$dumpvars
b0 .
b0 -
b101 ,
0+
x*
x)
x(
x'
0&
0%
0$
0#
0"
1!
$end
#5000
x%
x&
1+
b1 .
b1 -
1"
#10000
0"
#15000
0+
0%
0&
b10 -
b0 .
0(
0*
1"
#20000
0"
#25000
1+
b1 .
b11 -
1"
#30000
0"
#35000
0+
b100 -
b0 .
0'
0)
1"
#40000
0"
#45000
1+
0!
b1 .
b101 -
1"
#50000
0"
#55000
0+
b110 -
b0 .
1"
#60000
0"
#65000
1+
b1 .
b111 -
1"
#70000
0"
#75000
0+
b1000 -
b0 .
1"
#80000
0"
#85000
1+
b1 .
b1001 -
1"
#90000
0"
#95000
1!
0+
b0 -
b0 .
1"
#100000
0"
1$
#105000
1+
b1 .
b1 -
1"
#110000
0"
#115000
0+
0&
b10 -
b0 .
1*
1"
#120000
0"
#125000
1&
1+
b1 .
b11 -
1"
#130000
0"
#135000
0&
0+
b100 -
b110 ,
b0 .
1)
1"
#140000
0"
#145000
1+
b1 .
b101 -
1"
#150000
0"
#155000
0!
0+
b110 -
b0 .
1"
#160000
0"
#165000
1+
b1 .
b111 -
1"
#170000
0"
#175000
0+
b1000 -
b0 .
1"
#180000
0"
#185000
1+
b1 .
b1001 -
1"
#190000
0"
#195000
1!
0+
b0 -
b0 .
1"
#200000
0"
0$
#205000
1+
b1 .
b1 -
1"
#210000
0"
#215000
0+
b10 -
b0 .
0*
1"
#220000
0"
#225000
1+
b1 .
b11 -
1"
#230000
0"
#235000
0+
b100 -
b0 .
0)
1"
#240000
0"
#245000
1+
b1 .
b101 -
1"
#250000
0"
#255000
0!
0+
b110 -
b0 .
1"
#260000
0"
#265000
1+
b1 .
b111 -
1"
#270000
0"
#275000
0+
b1000 -
b0 .
1"
#280000
0"
#285000
1+
b1 .
b1001 -
1"
#290000
0"
#295000
1!
0+
b0 -
b0 .
1"
#300000
0"
1$
#305000
1+
b1 .
b1 -
1"
#310000
0"
#315000
0+
0&
b10 -
b0 .
1*
1"
#320000
0"
#325000
1&
1+
b1 .
b11 -
1"
#330000
0"
#335000
0&
0+
b100 -
b111 ,
b0 .
1)
1"
#340000
0"
#345000
1+
b1 .
b101 -
1"
#350000
0"
#355000
0+
b110 -
b0 .
1"
#360000
0"
#365000
1+
0!
b1 .
b111 -
1"
#370000
0"
#375000
0+
b1000 -
b0 .
1"
#380000
0"
#385000
1+
b1 .
b1001 -
1"
#390000
0"
#395000
1!
0+
b0 -
b0 .
1"
#400000
0"
0$
#405000
1+
b1 .
b1 -
1"
#410000
0"
#415000
0+
b10 -
b0 .
0*
1"
#420000
0"
#425000
1+
b1 .
b11 -
1"
#430000
0"
#435000
0+
b100 -
b0 .
0)
1"
#440000
0"
#445000
1+
b1 .
b101 -
1"
#450000
0"
#455000
0+
b110 -
b0 .
1"
#460000
0"
#465000
1+
0!
b1 .
b111 -
1"
#470000
0"
#475000
0+
b1000 -
b0 .
1"
#480000
0"
#485000
1+
b1 .
b1001 -
1"
#490000
0"
#495000
1!
0+
b0 -
b0 .
1"
#500000
0"
1$
#505000
1+
b1 .
b1 -
1"
#510000
0"
#515000
0+
0&
b10 -
b0 .
1*
1"
#520000
0"
#525000
1&
1+
b1 .
b11 -
1"
#530000
0"
#535000
0&
0+
b100 -
b1000 ,
b0 .
1)
1"
#540000
0"
#545000
1+
b1 .
b101 -
1"
#550000
0"
#555000
0+
b110 -
b0 .
1"
#560000
0"
#565000
1+
b1 .
b111 -
1"
#570000
0"
#575000
0!
0+
b1000 -
b0 .
1"
#580000
0"
#585000
1+
b1 .
b1001 -
1"
#590000
0"
#595000
1!
0+
b0 -
b0 .
1"
#600000
0"
0$
#605000
1+
b1 .
b1 -
1"
#610000
0"
#615000
0+
b10 -
b0 .
0*
1"
#620000
0"
#625000
1+
b1 .
b11 -
1"
#630000
0"
#635000
0+
b100 -
b0 .
0)
1"
#640000
0"
#645000
1+
b1 .
b101 -
1"
#650000
0"
#655000
0+
b110 -
b0 .
1"
#660000
0"
#665000
1+
b1 .
b111 -
1"
#670000
0"
#675000
0!
0+
b1000 -
b0 .
1"
#680000
0"
#685000
1+
b1 .
b1001 -
1"
#690000
0"
#695000
1!
0+
b0 -
b0 .
1"
#700000
0"
1$
#705000
1+
b1 .
b1 -
1"
#710000
0"
#715000
0+
0&
b10 -
b0 .
1*
1"
#720000
0"
#725000
1&
1+
b1 .
b11 -
1"
#730000
0"
#735000
0&
0+
b100 -
b1001 ,
b0 .
1)
1"
#740000
0"
#745000
1+
b1 .
b101 -
1"
#750000
0"
#755000
0+
b110 -
b0 .
1"
#760000
0"
#765000
1+
b1 .
b111 -
1"
#770000
0"
#775000
0+
b1000 -
b0 .
1"
#780000
0"
#785000
1+
0!
b1 .
b1001 -
1"
#790000
0"
#795000
1!
0+
b0 -
b0 .
1"
#800000
0"
0$
#805000
1+
b1 .
b1 -
1"
#810000
0"
#815000
0+
b10 -
b0 .
0*
1"
#820000
0"
#825000
1+
b1 .
b11 -
1"
#830000
0"
#835000
0+
b100 -
b0 .
0)
1"
#840000
0"
#845000
1+
b1 .
b101 -
1"
#850000
0"
#855000
0+
b110 -
b0 .
1"
#860000
0"
#865000
1+
b1 .
b111 -
1"
#870000
0"
#875000
0+
b1000 -
b0 .
1"
#880000
0"
#885000
1+
0!
b1 .
b1001 -
1"
#890000
0"
#895000
1!
0+
b0 -
b0 .
1"
#900000
0"
1$
#905000
1+
b1 .
b1 -
1"
#910000
0"
#915000
0+
0&
b10 -
b0 .
1*
1"
#920000
0"
#925000
1&
1+
b1 .
b11 -
1"
#930000
0"
#935000
0&
0+
b100 -
b1010 ,
b0 .
1)
1"
#940000
0"
#945000
1+
b1 .
b101 -
1"
#950000
0"
#955000
0+
b110 -
b0 .
1"
#960000
0"
#965000
1+
b1 .
b111 -
1"
#970000
0"
#975000
0+
b1000 -
b0 .
1"
#980000
0"
#985000
1+
b1 .
b1001 -
1"
#990000
0"
#995000
0+
b0 -
b0 .
1"
#1000000
0"
0$
#1005000
1+
b1 .
b1 -
1"
#1010000
0"
#1015000
0+
b10 -
b0 .
0*
1"
#1020000
0"
#1025000
1+
b1 .
b11 -
1"
#1030000
0"
#1035000
0+
b100 -
b0 .
0)
1"
#1040000
0"
#1045000
1+
b1 .
b101 -
1"
#1050000
0"
#1055000
0+
b110 -
b0 .
1"
#1060000
0"
#1065000
1+
b1 .
b111 -
1"
#1070000
0"
#1075000
0+
b1000 -
b0 .
1"
#1080000
0"
#1085000
1+
b1 .
b1001 -
1"
#1090000
0"
#1095000
0+
b0 -
b0 .
1"
#1100000
0"
1#
#1105000
1+
b1 .
b1 -
1"
#1110000
0"
#1115000
0+
0%
b10 -
b0 .
1(
1"
#1120000
0"
#1125000
1%
1+
b1 .
b11 -
1"
#1130000
0"
#1135000
0%
0+
b100 -
b1001 ,
b0 .
1'
1"
#1140000
0"
#1145000
1+
b1 .
b101 -
1"
#1150000
0"
#1155000
0+
b110 -
b0 .
1"
#1160000
0"
#1165000
1+
b1 .
b111 -
1"
#1170000
0"
#1175000
0+
b1000 -
b0 .
1"
#1180000
0"
#1185000
1+
0!
b1 .
b1001 -
1"
#1190000
0"
#1195000
1!
0+
b0 -
b0 .
1"
#1200000
0"
0#
#1205000
1+
b1 .
b1 -
1"
#1210000
0"
#1215000
0+
b10 -
b0 .
0(
1"
#1220000
0"
#1225000
1+
b1 .
b11 -
1"
#1230000
0"
#1235000
0+
b100 -
b0 .
0'
1"
#1240000
0"
#1245000
1+
b1 .
b101 -
1"
#1250000
0"
#1255000
0+
b110 -
b0 .
1"
#1260000
0"
#1265000
1+
b1 .
b111 -
1"
#1270000
0"
#1275000
0+
b1000 -
b0 .
1"
#1280000
0"
#1285000
1+
0!
b1 .
b1001 -
1"
#1290000
0"
#1295000
1!
0+
b0 -
b0 .
1"
#1300000
0"
1#
#1305000
1+
b1 .
b1 -
1"
#1310000
0"
#1315000
0+
0%
b10 -
b0 .
1(
1"
#1320000
0"
#1325000
1%
1+
b1 .
b11 -
1"
#1330000
0"
#1335000
0%
0+
b100 -
b1000 ,
b0 .
1'
1"
#1340000
0"
#1345000
1+
b1 .
b101 -
1"
#1350000
0"
#1355000
0+
b110 -
b0 .
1"
#1360000
0"
#1365000
1+
b1 .
b111 -
1"
#1370000
0"
#1375000
0!
0+
b1000 -
b0 .
1"
#1380000
0"
#1385000
1+
b1 .
b1001 -
1"
#1390000
0"
#1395000
1!
0+
b0 -
b0 .
1"
#1400000
0"
0#
#1405000
1+
b1 .
b1 -
1"
#1410000
0"
#1415000
0+
b10 -
b0 .
0(
1"
#1420000
0"
#1425000
1+
b1 .
b11 -
1"
#1430000
0"
#1435000
0+
b100 -
b0 .
0'
1"
#1440000
0"
#1445000
1+
b1 .
b101 -
1"
#1450000
0"
#1455000
0+
b110 -
b0 .
1"
#1460000
0"
#1465000
1+
b1 .
b111 -
1"
#1470000
0"
#1475000
0!
0+
b1000 -
b0 .
1"
#1480000
0"
#1485000
1+
b1 .
b1001 -
1"
#1490000
0"
#1495000
1!
0+
b0 -
b0 .
1"
#1500000
0"
1#
#1505000
1+
b1 .
b1 -
1"
#1510000
0"
#1515000
0+
0%
b10 -
b0 .
1(
1"
#1520000
0"
#1525000
1%
1+
b1 .
b11 -
1"
#1530000
0"
#1535000
0%
0+
b100 -
b111 ,
b0 .
1'
1"
#1540000
0"
#1545000
1+
b1 .
b101 -
1"
#1550000
0"
#1555000
0+
b110 -
b0 .
1"
#1560000
0"
#1565000
1+
0!
b1 .
b111 -
1"
#1570000
0"
#1575000
0+
b1000 -
b0 .
1"
#1580000
0"
#1585000
1+
b1 .
b1001 -
1"
#1590000
0"
#1595000
1!
0+
b0 -
b0 .
1"
#1600000
0"
0#
#1605000
1+
b1 .
b1 -
1"
#1610000
0"
#1615000
0+
b10 -
b0 .
0(
1"
#1620000
0"
#1625000
1+
b1 .
b11 -
1"
#1630000
0"
#1635000
0+
b100 -
b0 .
0'
1"
#1640000
0"
#1645000
1+
b1 .
b101 -
1"
#1650000
0"
#1655000
0+
b110 -
b0 .
1"
#1660000
0"
#1665000
1+
0!
b1 .
b111 -
1"
#1670000
0"
#1675000
0+
b1000 -
b0 .
1"
#1680000
0"
#1685000
1+
b1 .
b1001 -
1"
#1690000
0"
#1695000
1!
0+
b0 -
b0 .
1"
#1700000
0"
1#
#1705000
1+
b1 .
b1 -
1"
#1710000
0"
#1715000
0+
0%
b10 -
b0 .
1(
1"
#1720000
0"
#1725000
1%
1+
b1 .
b11 -
1"
#1730000
0"
#1735000
0%
0+
b100 -
b110 ,
b0 .
1'
1"
#1740000
0"
#1745000
1+
b1 .
b101 -
1"
#1750000
0"
#1755000
0!
0+
b110 -
b0 .
1"
#1760000
0"
#1765000
1+
b1 .
b111 -
1"
#1770000
0"
#1775000
0+
b1000 -
b0 .
1"
#1780000
0"
#1785000
1+
b1 .
b1001 -
1"
#1790000
0"
#1795000
1!
0+
b0 -
b0 .
1"
#1800000
0"
0#
#1805000
1+
b1 .
b1 -
1"
#1810000
0"
#1815000
0+
b10 -
b0 .
0(
1"
#1820000
0"
#1825000
1+
b1 .
b11 -
1"
#1830000
0"
#1835000
0+
b100 -
b0 .
0'
1"
#1840000
0"
#1845000
1+
b1 .
b101 -
1"
#1850000
0"
#1855000
0!
0+
b110 -
b0 .
1"
#1860000
0"
#1865000
1+
b1 .
b111 -
1"
#1870000
0"
#1875000
0+
b1000 -
b0 .
1"
#1880000
0"
#1885000
1+
b1 .
b1001 -
1"
#1890000
0"
#1895000
1!
0+
b0 -
b0 .
1"
#1900000
0"
1#
#1905000
1+
b1 .
b1 -
1"
#1910000
0"
#1915000
0+
0%
b10 -
b0 .
1(
1"
#1920000
0"
#1925000
1%
1+
b1 .
b11 -
1"
#1930000
0"
#1935000
0%
0+
b100 -
b101 ,
b0 .
1'
1"
#1940000
0"
#1945000
1+
0!
b1 .
b101 -
1"
#1950000
0"
#1955000
0+
b110 -
b0 .
1"
#1960000
0"
#1965000
1+
b1 .
b111 -
1"
#1970000
0"
#1975000
0+
b1000 -
b0 .
1"
#1980000
0"
#1985000
1+
b1 .
b1001 -
1"
#1990000
0"
#1995000
1!
0+
b0 -
b0 .
1"
#2000000
0"
0#
#2005000
1+
b1 .
b1 -
1"
#2010000
0"
#2015000
0+
b10 -
b0 .
0(
1"
#2020000
0"
#2025000
1+
b1 .
b11 -
1"
#2030000
0"
#2035000
0+
b100 -
b0 .
0'
1"
#2040000
0"
#2045000
1+
0!
b1 .
b101 -
1"
#2050000
0"
#2055000
0+
b110 -
b0 .
1"
#2060000
0"
#2065000
1+
b1 .
b111 -
1"
#2070000
0"
#2075000
0+
b1000 -
b0 .
1"
#2080000
0"
#2085000
1+
b1 .
b1001 -
1"
#2090000
0"
#2095000
1!
0+
b0 -
b0 .
1"
#2100000
0"
1#
#2105000
1+
b1 .
b1 -
1"
#2110000
0"
#2115000
0+
0%
b10 -
b0 .
1(
1"
#2120000
0"
#2125000
1%
1+
b1 .
b11 -
1"
#2130000
0"
#2135000
0%
0!
0+
b100 -
b100 ,
b0 .
1'
1"
#2140000
0"
#2145000
1+
b1 .
b101 -
1"
#2150000
0"
#2155000
0+
b110 -
b0 .
1"
#2160000
0"
#2165000
1+
b1 .
b111 -
1"
#2170000
0"
#2175000
0+
b1000 -
b0 .
1"
#2180000
0"
#2185000
1+
b1 .
b1001 -
1"
#2190000
0"
#2195000
1!
0+
b0 -
b0 .
1"
#2200000
0"
0#
#2205000
1+
b1 .
b1 -
1"
#2210000
0"
#2215000
0+
b10 -
b0 .
0(
1"
#2220000
0"
#2225000
1+
b1 .
b11 -
1"
#2230000
0"
#2235000
0!
0+
b100 -
b0 .
0'
1"
#2240000
0"
#2245000
1+
b1 .
b101 -
1"
#2250000
0"
#2255000
0+
b110 -
b0 .
1"
#2260000
0"
#2265000
1+
b1 .
b111 -
1"
#2270000
0"
#2275000
0+
b1000 -
b0 .
1"
#2280000
0"
#2285000
1+
b1 .
b1001 -
1"
#2290000
0"
#2295000
1!
0+
b0 -
b0 .
1"
#2300000
0"
1#
#2305000
1+
b1 .
b1 -
1"
#2310000
0"
#2315000
0+
0%
b10 -
b0 .
1(
1"
#2320000
0"
#2325000
1%
1+
b1 .
b11 -
1"
#2330000
0"
#2335000
0%
0!
0+
b100 -
b11 ,
b0 .
1'
1"
#2340000
0"
#2345000
1+
b1 .
b101 -
1"
#2350000
0"
#2355000
0+
b110 -
b0 .
1"
#2360000
0"
#2365000
1+
b1 .
b111 -
1"
#2370000
0"
#2375000
0+
b1000 -
b0 .
1"
#2380000
0"
#2385000
1+
b1 .
b1001 -
1"
#2390000
0"
#2395000
1!
0+
b0 -
b0 .
1"
#2400000
0"
0#
#2405000
1+
b1 .
b1 -
1"
#2410000
0"
#2415000
0+
b10 -
b0 .
0(
1"
#2420000
0"
#2425000
1+
0!
b1 .
b11 -
1"
#2430000
0"
#2435000
0+
b100 -
b0 .
0'
1"
#2440000
0"
#2445000
1+
b1 .
b101 -
1"
#2450000
0"
#2455000
0+
b110 -
b0 .
1"
#2460000
0"
#2465000
1+
b1 .
b111 -
1"
#2470000
0"
#2475000
0+
b1000 -
b0 .
1"
#2480000
0"
#2485000
1+
b1 .
b1001 -
1"
#2490000
0"
#2495000
1!
0+
b0 -
b0 .
1"
#2500000
0"
1#
#2505000
1+
b1 .
b1 -
1"
#2510000
0"
#2515000
0+
0%
b10 -
b0 .
1(
1"
#2520000
0"
#2525000
1%
1+
0!
b1 .
b11 -
1"
#2530000
0"
#2535000
0%
0+
b100 -
b10 ,
b0 .
1'
1"
#2540000
0"
#2545000
1+
b1 .
b101 -
1"
#2550000
0"
#2555000
0+
b110 -
b0 .
1"
#2560000
0"
#2565000
1+
b1 .
b111 -
1"
#2570000
0"
#2575000
0+
b1000 -
b0 .
1"
#2580000
0"
#2585000
1+
b1 .
b1001 -
1"
#2590000
0"
#2595000
1!
0+
b0 -
b0 .
1"
#2600000
0"
0#
#2605000
1+
b1 .
b1 -
1"
#2610000
0"
#2615000
0!
0+
b10 -
b0 .
0(
1"
#2620000
0"
#2625000
1+
b1 .
b11 -
1"
#2630000
0"
#2635000
0+
b100 -
b0 .
0'
1"
#2640000
0"
#2645000
1+
b1 .
b101 -
1"
#2650000
0"
#2655000
0+
b110 -
b0 .
1"
#2660000
0"
#2665000
1+
b1 .
b111 -
1"
#2670000
0"
#2675000
0+
b1000 -
b0 .
1"
#2680000
0"
#2685000
1+
b1 .
b1001 -
1"
#2690000
0"
#2695000
1!
0+
b0 -
b0 .
1"
#2700000
0"
1#
#2705000
1+
b1 .
b1 -
1"
#2710000
0"
#2715000
0!
0+
0%
b10 -
b0 .
1(
1"
#2720000
0"
#2725000
1%
1+
b1 .
b11 -
1"
#2730000
0"
#2735000
0%
0+
b100 -
b1 ,
b0 .
1'
1"
#2740000
0"
#2745000
1+
b1 .
b101 -
1"
#2750000
0"
#2755000
0+
b110 -
b0 .
1"
#2760000
0"
#2765000
1+
b1 .
b111 -
1"
#2770000
0"
#2775000
0+
b1000 -
b0 .
1"
#2780000
0"
#2785000
1+
b1 .
b1001 -
1"
#2790000
0"
#2795000
1!
0+
b0 -
b0 .
1"
#2800000
0"
0#
#2805000
1+
0!
b1 .
b1 -
1"
#2810000
0"
#2815000
0+
b10 -
b0 .
0(
1"
#2820000
0"
#2825000
1+
b1 .
b11 -
1"
#2830000
0"
#2835000
0+
b100 -
b0 .
0'
1"
#2840000
0"
#2845000
1+
b1 .
b101 -
1"
#2850000
0"
#2855000
0+
b110 -
b0 .
1"
#2860000
0"
#2865000
1+
b1 .
b111 -
1"
#2870000
0"
#2875000
0+
b1000 -
b0 .
1"
#2880000
0"
#2885000
1+
b1 .
b1001 -
1"
#2890000
0"
#2895000
1!
0+
b0 -
b0 .
1"
